ollama_agent/__init__.py
ollama_agent/agent.py
ollama_agent/config.py
ollama_agent/exceptions.py
ollama_agent/tools.py
ollama_agent-0.1.4.dist-info/licenses/LICENSE
ollama_agent-0.1.4.dist-info/METADATA
ollama_agent-0.1.4.dist-info/WHEEL
ollama_agent-0.1.4.dist-info/top_level.txt
ollama_agent-0.1.4.dist-info/RECORD
