Metadata-Version: 2.4
Name: ollama-agent
Version: 0.1.4
Summary: A lightweight AI agent library powered by Ollama with built-in tools and custom tool support
Author: Aashish Thapa
License-Expression: MIT
Project-URL: Homepage, https://github.com/aashish-thapa/ollama-agent
Project-URL: Repository, https://github.com/aashish-thapa/ollama-agent
Project-URL: Issues, https://github.com/aashish-thapa/ollama-agent/issues
Keywords: ollama,agent,ai,llm,langchain,tools
Classifier: Development Status :: 4 - Beta
Classifier: Intended Audience :: Developers
Classifier: Operating System :: OS Independent
Classifier: Programming Language :: Python :: 3
Classifier: Programming Language :: Python :: 3.10
Classifier: Programming Language :: Python :: 3.11
Classifier: Programming Language :: Python :: 3.12
Classifier: Programming Language :: Python :: 3.13
Classifier: Topic :: Scientific/Engineering :: Artificial Intelligence
Requires-Python: >=3.10
License-File: LICENSE
Requires-Dist: langchain-ollama>=0.2.0
Requires-Dist: langchain-core>=0.3.0
Requires-Dist: ddgs>=6.0.0
Requires-Dist: python-dotenv>=1.0.0
Provides-Extra: dev
Requires-Dist: pytest>=7.0.0; extra == "dev"
Requires-Dist: pytest-cov>=4.0.0; extra == "dev"
Requires-Dist: black>=23.0.0; extra == "dev"
Requires-Dist: ruff>=0.1.0; extra == "dev"
Dynamic: license-file
